lavavu/LavaVuPython.py
lavavu/_LavaVuPython.cpython-310-x86_64-linux-gnu.so
lavavu/__init__.py
lavavu/__main__.py
lavavu/amalgamate.py
lavavu/aserver.py
lavavu/control.py
lavavu/convert.py
lavavu/dict.json
lavavu/font.bin
lavavu/lavavu.py
lavavu/points.py
lavavu/server.py
lavavu/tracers.py
lavavu/vutils.py
lavavu/html/LavaVu-amalgamated.css
lavavu/html/OK-min.js
lavavu/html/baseviewer.js
lavavu/html/control.css
lavavu/html/control.js
lavavu/html/dat-gui-light-theme.css
lavavu/html/dat.gui.min.js
lavavu/html/draw.js
lavavu/html/drawbox.js
lavavu/html/emscripten-template.js
lavavu/html/emscripten.css
lavavu/html/favicon.ico
lavavu/html/gl-matrix-min.js
lavavu/html/gui.css
lavavu/html/menu.js
lavavu/html/server.js
lavavu/html/stats.min.js
lavavu/html/styles.css
lavavu/html/webview-template.html
lavavu/html/webview.html
lavavu/osmesa/LavaVuPython.py
lavavu/osmesa/_LavaVuPython.cpython-310-x86_64-linux-gnu.so
lavavu/osmesa/__init__.py
lavavu/shaders/default.frag
lavavu/shaders/default.vert
lavavu/shaders/fontShader.frag
lavavu/shaders/fontShader.vert
lavavu/shaders/lineShader.frag
lavavu/shaders/lineShader.vert
lavavu/shaders/pointShader.frag
lavavu/shaders/pointShader.vert
lavavu/shaders/triShader.frag
lavavu/shaders/triShader.vert
lavavu/shaders/volumeShader.frag
lavavu/shaders/volumeShader.vert
lavavu_osmesa.libs/libLLVM-17-51492e70.so
lavavu_osmesa.libs/libOSMesa-f6a8f160.so.8.0.0
lavavu_osmesa.libs/libdrm-b0291a67.so.2.4.0
lavavu_osmesa.libs/libffi-3a37023a.so.6.0.2
lavavu_osmesa.libs/libglapi-520b284c.so.0.0.0
lavavu_osmesa.libs/libpcre2-8-516f4c9d.so.0.7.1
lavavu_osmesa.libs/libselinux-d0805dcb.so.1
lavavu_osmesa.libs/libtinfo-3a2cb85b.so.6.1
lavavu_osmesa.libs/libzstd-76b78bac.so.1.4.4
lavavu_osmesa-1.9.9.dist-info/METADATA
lavavu_osmesa-1.9.9.dist-info/WHEEL
lavavu_osmesa-1.9.9.dist-info/entry_points.txt
lavavu_osmesa-1.9.9.dist-info/top_level.txt
lavavu_osmesa-1.9.9.dist-info/RECORD
lavavu_osmesa-1.9.9.dist-info/licenses/LICENSE.md
