Metadata-Version: 2.4
Name: lavavu-osmesa
Version: 1.9.9
Summary: Python interface to LavaVu OpenGL 3D scientific visualisation utilities
Author-email: Owen Kaluza <owen@kaluza.id.au>
License: ### Licensing
Project-URL: Documentation, https://lavavu.github.io
Project-URL: Source, https://github.com/lavavu/LavaVu
Classifier: License :: OSI Approved :: GNU Lesser General Public License v3 (LGPLv3)
Classifier: Intended Audience :: Developers
Classifier: Intended Audience :: Science/Research
Classifier: Operating System :: POSIX :: Linux
Classifier: Operating System :: MacOS
Classifier: Operating System :: Microsoft :: Windows
Classifier: Environment :: X11 Applications
Classifier: Environment :: MacOS X :: Cocoa
Classifier: Environment :: Win32 (MS Windows)
Classifier: Topic :: Multimedia :: Graphics :: 3D Rendering
Classifier: Topic :: Scientific/Engineering :: Visualization
Classifier: Development Status :: 5 - Production/Stable
Classifier: Programming Language :: C++
Classifier: Programming Language :: Python :: 3
Classifier: Programming Language :: Python :: 3.6
Classifier: Programming Language :: Python :: 3.7
Classifier: Programming Language :: Python :: 3.8
Classifier: Programming Language :: Python :: 3.9
Classifier: Programming Language :: Python :: 3.10
Classifier: Programming Language :: Python :: 3.11
Classifier: Programming Language :: Python :: 3.12
Classifier: Programming Language :: Python :: 3 :: Only
Classifier: Framework :: Jupyter
Classifier: Framework :: IPython
Requires-Python: >=3.5
License-File: LICENSE.md
Requires-Dist: numpy>=1.18
Requires-Dist: aiohttp
Requires-Dist: jupyter_server_proxy
Requires-Dist: matplotlib
Requires-Dist: numpy-quaternion
Dynamic: license-file
